{"nodes": [{"id": "c_users_public_documents_cdc_app_src_main_java_com_vikasyadavnsit_cdc_permissions_permissionhandler_java", "label": "PermissionHandler.java", "file_type": "code", "source_file": "C:\\Users\\Public\\Documents\\CDC\\app\\src\\main\\java\\com\\vikasyadavnsit\\cdc\\permissions\\PermissionHandler.java", "source_location": "L1"}, {"id": "permissions_permissionhandler_permissionhandler", "label": "PermissionHandler", "file_type": "code", "source_file": "C:\\Users\\Public\\Documents\\CDC\\app\\src\\main\\java\\com\\vikasyadavnsit\\cdc\\permissions\\PermissionHandler.java", "source_location": "L9"}, {"id": "permissions_permissionhandler_permissionhandler_haspermission", "label": ".hasPermission()", "file_type": "code", "source_file": "C:\\Users\\Public\\Documents\\CDC\\app\\src\\main\\java\\com\\vikasyadavnsit\\cdc\\permissions\\PermissionHandler.java", "source_location": "L10"}, {"id": "permissions_permissionhandler_permissionhandler_requestpermission", "label": ".requestPermission()", "file_type": "code", "source_file": "C:\\Users\\Public\\Documents\\CDC\\app\\src\\main\\java\\com\\vikasyadavnsit\\cdc\\permissions\\PermissionHandler.java", "source_location": "L12"}, {"id": "permissions_permissionhandler_permissionhandler_requestallpermissions", "label": ".requestAllPermissions()", "file_type": "code", "source_file": "C:\\Users\\Public\\Documents\\CDC\\app\\src\\main\\java\\com\\vikasyadavnsit\\cdc\\permissions\\PermissionHandler.java", "source_location": "L14"}, {"id": "permissions_permissionhandler_permissionhandler_handlepermissionresult", "label": ".handlePermissionResult()", "file_type": "code", "source_file": "C:\\Users\\Public\\Documents\\CDC\\app\\src\\main\\java\\com\\vikasyadavnsit\\cdc\\permissions\\PermissionHandler.java", "source_location": "L16"}, {"id": "permissions_permissionhandler_permissionhandler_resetallpermissionmanually", "label": ".resetAllPermissionManually()", "file_type": "code", "source_file": "C:\\Users\\Public\\Documents\\CDC\\app\\src\\main\\java\\com\\vikasyadavnsit\\cdc\\permissions\\PermissionHandler.java", "source_location": "L18"}], "edges": [{"source": "c_users_public_documents_cdc_app_src_main_java_com_vikasyadavnsit_cdc_permissions_permissionhandler_java", "target": "activity", "relation": "imports", "context": "import", "confidence": "EXTRACTED", "source_file": "C:\\Users\\Public\\Documents\\CDC\\app\\src\\main\\java\\com\\vikasyadavnsit\\cdc\\permissions\\PermissionHandler.java", "source_location": "L4", "weight": 1.0}, {"source": "c_users_public_documents_cdc_app_src_main_java_com_vikasyadavnsit_cdc_permissions_permissionhandler_java", "target": "context", "relation": "imports", "context": "import", "confidence": "EXTRACTED", "source_file": "C:\\Users\\Public\\Documents\\CDC\\app\\src\\main\\java\\com\\vikasyadavnsit\\cdc\\permissions\\PermissionHandler.java", "source_location": "L5", "weight": 1.0}, {"source": "c_users_public_documents_cdc_app_src_main_java_com_vikasyadavnsit_cdc_permissions_permissionhandler_java", "target": "permissiontype", "relation": "imports", "context": "import", "confidence": "EXTRACTED", "source_file": "C:\\Users\\Public\\Documents\\CDC\\app\\src\\main\\java\\com\\vikasyadavnsit\\cdc\\permissions\\PermissionHandler.java", "source_location": "L7", "weight": 1.0}, {"source": "c_users_public_documents_cdc_app_src_main_java_com_vikasyadavnsit_cdc_permissions_permissionhandler_java", "target": "permissions_permissionhandler_permissionhandler", "relation": "contains", "confidence": "EXTRACTED", "source_file": "C:\\Users\\Public\\Documents\\CDC\\app\\src\\main\\java\\com\\vikasyadavnsit\\cdc\\permissions\\PermissionHandler.java", "source_location": "L9", "weight": 1.0}, {"source": "permissions_permissionhandler_permissionhandler", "target": "permissions_permissionhandler_permissionhandler_haspermission", "relation": "method", "confidence": "EXTRACTED", "source_file": "C:\\Users\\Public\\Documents\\CDC\\app\\src\\main\\java\\com\\vikasyadavnsit\\cdc\\permissions\\PermissionHandler.java", "source_location": "L10", "weight": 1.0}, {"source": "permissions_permissionhandler_permissionhandler", "target": "permissions_permissionhandler_permissionhandler_requestpermission", "relation": "method", "confidence": "EXTRACTED", "source_file": "C:\\Users\\Public\\Documents\\CDC\\app\\src\\main\\java\\com\\vikasyadavnsit\\cdc\\permissions\\PermissionHandler.java", "source_location": "L12", "weight": 1.0}, {"source": "permissions_permissionhandler_permissionhandler", "target": "permissions_permissionhandler_permissionhandler_requestallpermissions", "relation": "method", "confidence": "EXTRACTED", "source_file": "C:\\Users\\Public\\Documents\\CDC\\app\\src\\main\\java\\com\\vikasyadavnsit\\cdc\\permissions\\PermissionHandler.java", "source_location": "L14", "weight": 1.0}, {"source": "permissions_permissionhandler_permissionhandler", "target": "permissions_permissionhandler_permissionhandler_handlepermissionresult", "relation": "method", "confidence": "EXTRACTED", "source_file": "C:\\Users\\Public\\Documents\\CDC\\app\\src\\main\\java\\com\\vikasyadavnsit\\cdc\\permissions\\PermissionHandler.java", "source_location": "L16", "weight": 1.0}, {"source": "permissions_permissionhandler_permissionhandler", "target": "permissions_permissionhandler_permissionhandler_resetallpermissionmanually", "relation": "method", "confidence": "EXTRACTED", "source_file": "C:\\Users\\Public\\Documents\\CDC\\app\\src\\main\\java\\com\\vikasyadavnsit\\cdc\\permissions\\PermissionHandler.java", "source_location": "L18", "weight": 1.0}], "raw_calls": []}